LICENSE
pma/__init__.py
pma/__main__.py
pma/classes.py
pma/cli.py
pma/exceptions.py
pma/plcs.json
pma-2.0.2.dist-info/entry_points.txt
pma-2.0.2.dist-info/LICENSE
pma-2.0.2.dist-info/WHEEL
pma-2.0.2.dist-info/METADATA
pma-2.0.2.dist-info/RECORD
