Metadata-Version: 2.1
Name: pma
Version: 2.0.2
Summary: Farm points on PiXL Maths App
Home-page: https://github.com/nihaals/pixl-maths-app-farm
License: MIT
Author: Nihaal Sangha
Author-email: me@niha.al
Requires-Python: >=3.8,<4.0
Classifier: License :: OSI Approved :: MIT License
Classifier: Programming Language :: Python :: 3
Classifier: Programming Language :: Python :: 3.8
Requires-Dist: click (>=7.1.2,<8.0.0)
Requires-Dist: requests (>=2.23.0,<3.0.0)
Project-URL: Repository, https://github.com/nihaals/pixl-maths-app-farm
